envguard/__init__.py
envguard/cli.py
envguard/core.py
envguard/crypto.py
envguard/exceptions.py
envguard/secrets.py
envgd-0.1.2.dist-info/METADATA
envgd-0.1.2.dist-info/WHEEL
envgd-0.1.2.dist-info/entry_points.txt
envgd-0.1.2.dist-info/licenses/LICENSE
envgd-0.1.2.dist-info/RECORD
