Metadata-Version: 2.4
Name: envgd
Version: 0.1.2
Summary: Safe Environment Variable Loader
Project-URL: Source, https://github.com/moogleLabsDev/ENV-Guard
Author-email: MoogleLabs <mooglelabs.developers@gmail.com>
License-Expression: MIT
License-File: LICENSE
Keywords: configuration,dotenv,environment,security,variables
Classifier: Development Status :: 4 - Beta
Classifier: Programming Language :: Python
Classifier: Programming Language :: Python :: 3.8
Classifier: Programming Language :: Python :: 3.9
Classifier: Programming Language :: Python :: 3.10
Classifier: Programming Language :: Python :: 3.11
Classifier: Programming Language :: Python :: 3.12
Classifier: Programming Language :: Python :: 3.13
Classifier: Programming Language :: Python :: 3.14
Classifier: Topic :: Security
Requires-Python: >=3.8
Requires-Dist: cryptography>=41.0.0
Provides-Extra: aws
Requires-Dist: boto3>=1.26.0; extra == 'aws'
Provides-Extra: dev
Requires-Dist: build; extra == 'dev'
Requires-Dist: pydantic>=2.0.0; extra == 'dev'
Requires-Dist: pytest; extra == 'dev'
Requires-Dist: pytest-cov; extra == 'dev'
Requires-Dist: twine; extra == 'dev'
Provides-Extra: pydantic
Requires-Dist: pydantic>=2.0.0; extra == 'pydantic'
Provides-Extra: secrets
Requires-Dist: boto3>=1.26.0; extra == 'secrets'
Requires-Dist: hvac>=1.0.0; extra == 'secrets'
Provides-Extra: vault
Requires-Dist: hvac>=1.0.0; extra == 'vault'
